dicom_validator/__init__.py
dicom_validator/dump_dcm_info.py
dicom_validator/tag_tools.py
dicom_validator/validate_iods.py
dicom_validator/spec_reader/__init__.py
dicom_validator/spec_reader/condition.py
dicom_validator/spec_reader/condition_grammar.py
dicom_validator/spec_reader/condition_parser.py
dicom_validator/spec_reader/edition_reader.py
dicom_validator/spec_reader/enum_parser.py
dicom_validator/spec_reader/part3_reader.py
dicom_validator/spec_reader/part4_reader.py
dicom_validator/spec_reader/part6_reader.py
dicom_validator/spec_reader/serializer.py
dicom_validator/spec_reader/spec_reader.py
dicom_validator/tests/__init__.py
dicom_validator/tests/test_cmdline_tools.py
dicom_validator/tests/utils.py
dicom_validator/tests/spec_reader/__init__.py
dicom_validator/tests/spec_reader/conftest.py
dicom_validator/tests/spec_reader/test_condition.py
dicom_validator/tests/spec_reader/test_condition_parser.py
dicom_validator/tests/spec_reader/test_edition_reader.py
dicom_validator/tests/spec_reader/test_enum_parser.py
dicom_validator/tests/spec_reader/test_part3_reader.py
dicom_validator/tests/spec_reader/test_part4_reader.py
dicom_validator/tests/spec_reader/test_part6_reader.py
dicom_validator/tests/spec_reader/test_spec_reader.py
dicom_validator/tests/validator/__init__.py
dicom_validator/tests/validator/conftest.py
dicom_validator/tests/validator/test_dicom_file_validator.py
dicom_validator/tests/validator/test_iod_validator.py
dicom_validator/tests/validator/test_iod_validator_func_groups.py
dicom_validator/validator/__init__.py
dicom_validator/validator/dicom_file_validator.py
dicom_validator/validator/iod_validator.py
dicom_validator-0.7.3.dist-info/licenses/LICENSE
dicom_validator-0.7.3.dist-info/METADATA
dicom_validator-0.7.3.dist-info/WHEEL
dicom_validator-0.7.3.dist-info/entry_points.txt
dicom_validator-0.7.3.dist-info/top_level.txt
dicom_validator-0.7.3.dist-info/RECORD
