Metadata-Version: 2.4
Name: dicom-validator
Version: 0.7.3
Summary: Python DICOM validator using input from DICOM specs in docbook format
Author-email: mrbean-bremen and contributors <hansemrbean@googlemail.com>
License: MIT
Project-URL: documentation, https://github.com/pydicom/dicom-validator#readme
Project-URL: download, https://github.com/pydicom/dicom-validator/archive/main.zip
Project-URL: homepage, https://github.com/pydicom/dicom-validator
Project-URL: repository, https://github.com/pydicom/dicom-validator
Keywords: dicom, python
Classifier: License :: OSI Approved :: MIT License
Classifier: Intended Audience :: Developers
Classifier: Intended Audience :: Healthcare Industry
Classifier: Development Status :: 4 - Beta
Classifier: Environment :: Console
Classifier: Programming Language :: Python
Classifier: Programming Language :: Python :: 3.9
Classifier: Programming Language :: Python :: 3.10
Classifier: Programming Language :: Python :: 3.11
Classifier: Programming Language :: Python :: 3.12
Classifier: Programming Language :: Python :: 3.13
Classifier: Operating System :: POSIX :: Linux
Classifier: Operating System :: MacOS
Classifier: Operating System :: Microsoft :: Windows
Classifier: Topic :: Scientific/Engineering :: Medical Science Apps.
Requires-Python: >=3.9
License-File: LICENSE
Requires-Dist: pydicom>=2.3
Requires-Dist: lxml
Requires-Dist: pyparsing>=3.2
Provides-Extra: dev
Requires-Dist: pyfakefs>=5.0.0; extra == "dev"
Requires-Dist: pytest; extra == "dev"
Requires-Dist: pytest-order; extra == "dev"
Dynamic: license-file
